django_name-2.0.0.dist-info/METADATA
django_name-2.0.0.dist-info/RECORD
django_name-2.0.0.dist-info/WHEEL
django_name-2.0.0.dist-info/top_level.txt
name/__init__.py
name/admin.py
name/app_settings.py
name/context_processors.py
name/decorators.py
name/feeds.py
name/models.py
name/urls.py
name/utils.py
name/validators.py
name/views.py
name/api/__init__.py
name/api/serializers.py
name/api/stats.py
name/api/views.py
name/fixtures/identifier_types.json
name/migrations/0001_initial.py
name/migrations/0002_change_choice_fields.py
name/migrations/0003_auto_20180917_2221.py
name/migrations/__init__.py
name/static/name/css/name.css
name/static/name/icons/academia_favicon.ico
name/static/name/icons/facebook_favicon.ico
name/static/name/icons/google_scholar_favicon.ico
name/static/name/icons/linkedinfavicon.png
name/static/name/icons/loc_fav.ico
name/static/name/icons/orcid_favicon.ico
name/static/name/icons/rg_favicon.ico
name/static/name/icons/scopus_favicon.ico
name/static/name/icons/tumblr_favicon.ico
name/static/name/icons/twitter_favicon.ico
name/static/name/icons/viaf_favicon.ico
name/static/name/icons/wikipedia_favicon.ico
name/static/name/img/favicon.png
name/static/name/js/ajax-form.js
name/static/name/js/map.js
name/static/name/js/stats.js
name/templates/name/_navbar.html
name/templates/name/_pagination.html
name/templates/name/about.html
name/templates/name/base.html
name/templates/name/introduction.html
name/templates/name/landing.html
name/templates/name/map.html
name/templates/name/name.mads.xml
name/templates/name/name_detail.html
name/templates/name/opensearch.xml
name/templates/name/search.html
name/templates/name/stats.html
name/templatetags/__init__.py
name/templatetags/name_extras.py
