Metadata-Version: 2.1
Name: django-name
Version: 2.0.0
Summary: Name Authority App for Django.
Home-page: https://github.com/unt-libraries/django-name
Author: University of North Texas Libraries
Author-email: mark.phillips@unt.edu
License: BSD
Keywords: django name citation
Platform: UNKNOWN
Classifier: Environment :: Web Environment
Classifier: Framework :: Django
Classifier: Intended Audience :: End Users/Desktop
Classifier: Natural Language :: English
Classifier: Programming Language :: Python
Classifier: Programming Language :: Python :: 2.7
Classifier: Topic :: Internet :: WWW/HTTP :: WSGI :: Application
Requires-Dist: python-dateutil (==2.7.3)
Requires-Dist: markdown2 (==2.3.5)
Requires-Dist: djangorestframework (==3.8)
Requires-Dist: pynaco (==0.1.0)
